psycopg2_mq/__init__.py
psycopg2_mq/model.py
psycopg2_mq/source.py
psycopg2_mq/trigger.py
psycopg2_mq/util.py
psycopg2_mq/worker.py
psycopg2_mq-0.13.5.dist-info/licenses/LICENSE.txt
psycopg2_mq-0.13.5.dist-info/METADATA
psycopg2_mq-0.13.5.dist-info/WHEEL
psycopg2_mq-0.13.5.dist-info/top_level.txt
psycopg2_mq-0.13.5.dist-info/RECORD
