Metadata-Version: 2.4
Name: psycopg2_mq
Version: 0.13.5
Summary: A message queue written around PostgreSQL.
Home-page: https://github.com/mmerickel/psycopg2_mq
Author: Michael Merickel
Author-email: oss@m.merickel.org
Keywords: psycopg2,postgres,postgresql,message queue,background jobs
Classifier: Development Status :: 4 - Beta
Classifier: Intended Audience :: Developers
Classifier: License :: OSI Approved :: MIT License
Classifier: Natural Language :: English
Classifier: Programming Language :: Python :: 3
Classifier: Programming Language :: Python :: 3.9
Classifier: Programming Language :: Python :: 3.10
Classifier: Programming Language :: Python :: 3.11
Classifier: Programming Language :: Python :: 3.12
Classifier: Programming Language :: Python :: 3.13
Classifier: Programming Language :: Python :: Implementation :: CPython
Requires-Python: >=3.9
License-File: LICENSE.txt
Requires-Dist: python-dateutil
Requires-Dist: SQLAlchemy>=1.4
Requires-Dist: transaction
Requires-Dist: zope.sqlalchemy
Provides-Extra: testing
Requires-Dist: psycopg[binary]; extra == "testing"
Requires-Dist: psycopg2-binary; extra == "testing"
Requires-Dist: pytest; extra == "testing"
Requires-Dist: pytest-cov; extra == "testing"
Requires-Dist: pytest-env; extra == "testing"
Requires-Dist: pytest-postgresql; extra == "testing"
Dynamic: license-file
